{
  "date": "2026-04-11",
  "proposals": [
    {
      "ticker": "LLY",
      "strategy": "LONG_CALL",
      "iv_rank": 22.222222222222225,
      "direction": "BULLISH",
      "option": {
        "expiry": "2026-08-21",
        "strike": 980.0,
        "bid": 74.0,
        "ask": 77.3,
        "last": 85.4,
        "open_interest": 255,
        "implied_vol": 0.41737948348999016,
        "spread_ratio": 0.0427,
        "dte": 131
      },
      "features": {
        "impact": 4,
        "surprise": 2,
        "mismatch": 0.595,
        "z_score": 0.681,
        "sigma_30d": 0.0213,
        "eps_drift": 0.0,
        "bin_impact": "low",
        "bin_mismatch": "weak",
        "bin_eps_drift": "noise"
      },
      "simulation": {
        "hit_rate": 0.9717,
        "n_paths": 10000,
        "n_days": 120,
        "target_price": 1033.42,
        "current_price": 939.47,
        "sigma_adj": 0.0192,
        "sector": "Healthcare",
        "ttm": "4-8 Wochen"
      },
      "deep_analysis": {
        "ticker": "LLY",
        "impact": 4,
        "surprise": 2,
        "mispricing_logic": "Der Markt reagiert auf Indien-spezifische Generika-Konkurrenz bei GLP-1s als w\u00e4ren US/EU-Revenues betroffen. Strukturell falsch: LLY h\u00e4lt keine dominante Position in Indien, Tirzepatid-Patentschutz in Kernm\u00e4rkten bleibt intakt bis 2036+. Die -1.45% Bewegung \u00fcbergewichtet einen geografisch marginalen Markt mit niedrigen ASPs. EPS-Drift von 0.0 signalisiert, dass Analysten ihre Sch\u00e4tzungen nicht anpassen \u2013 kongruent mit 'no fundamental change'-These.",
        "catalyst": "LLY Q2 2025 Earnings (voraussichtlich Juli/August 2025): Mounjaro/Zepbound US-Volumendaten werden Indien-Narrativ widerlegen; Supply-Normalisierung und Formulary-Wins als positiver Offset.",
        "time_to_materialization": "4-8 Wochen",
        "bear_case": "Indien als Blaupause: Komprimierter Pricing-Druck setzt sich in Emerging Markets fort, belastet LLY's Wachstumsstory in Schwellenl\u00e4ndern strukturell und signalisiert fr\u00fchere als erwartete Generika-Erosion in globalen M\u00e4rkten.",
        "bear_case_severity": 3,
        "direction": "BULLISH"
      },
      "final_score": 0.1668
    }
  ]
}