{
  "feature_stats": {
    "impact": {
      "low": {
        "count": 127,
        "avg_return": 0.0
      },
      "mid": {
        "count": 283,
        "avg_return": 0.0
      },
      "high": {
        "count": 55,
        "avg_return": 0.0
      }
    },
    "mismatch": {
      "weak": {
        "count": 258,
        "avg_return": 0.0
      },
      "good": {
        "count": 195,
        "avg_return": 0.0
      },
      "strong": {
        "count": 12,
        "avg_return": 0.0
      }
    },
    "eps_drift": {
      "noise": {
        "count": 465,
        "avg_return": 0.0
      },
      "relevant": {
        "count": 0,
        "avg_return": 0.0
      },
      "massive": {
        "count": 0,
        "avg_return": 0.0
      }
    }
  },
  "active_trades": [
    {
      "ticker": "LLY",
      "entry_date": "2026-04-11",
      "features": {
        "impact": 8,
        "surprise": 6,
        "mismatch": 4.595,
        "z_score": 0.681,
        "sigma_30d": 0.0213,
        "eps_drift": 0.0,
        "bin_impact": "high",
        "bin_mismatch": "good",
        "bin_eps_drift": "noise"
      },
      "strategy": "LONG_CALL",
      "option": {
        "expiry": "2026-08-21",
        "strike": 980.0,
        "bid": 74.0,
        "ask": 77.3,
        "last": 85.4,
        "open_interest": 255,
        "implied_vol": 0.41737948348999016,
        "spread_ratio": 0.0427,
        "dte": 131
      },
      "outcome": null,
      "last_price": 881.5725,
      "current_return": 0.0
    },
    {
      "ticker": "META",
      "entry_date": "2026-04-11",
      "features": {
        "impact": 6,
        "surprise": 7,
        "mismatch": 0.733,
        "z_score": 1.053,
        "sigma_30d": 0.027,
        "eps_drift": 0.0,
        "bin_impact": "mid",
        "bin_mismatch": "weak",
        "bin_eps_drift": "noise"
      },
      "strategy": "LONG_CALL",
      "option": {
        "expiry": "2026-08-21",
        "strike": 700.0,
        "bid": 33.0,
        "ask": 33.4,
        "last": 33.35,
        "open_interest": 2204,
        "implied_vol": 0.390203851928711,
        "spread_ratio": 0.012,
        "dte": 131
      },
      "outcome": null,
      "last_price": 669.105,
      "current_return": 0.0
    },
    {
      "ticker": "MRK",
      "entry_date": "2026-04-11",
      "features": {
        "impact": 7,
        "surprise": 6,
        "mismatch": 2.158,
        "z_score": 0.968,
        "sigma_30d": 0.0148,
        "eps_drift": 0.0,
        "bin_impact": "mid",
        "bin_mismatch": "weak",
        "bin_eps_drift": "noise"
      },
      "strategy": "LONG_CALL",
      "option": {
        "expiry": "2026-09-18",
        "strike": 130.0,
        "bid": 6.0,
        "ask": 6.2,
        "last": 6.05,
        "open_interest": 2663,
        "implied_vol": 0.2979196185302734,
        "spread_ratio": 0.0323,
        "dte": 159
      },
      "outcome": null,
      "last_price": 112.42,
      "current_return": 0.0
    },
    {
      "ticker": "AAPL",
      "entry_date": "2026-04-11",
      "features": {
        "impact": 4,
        "surprise": 3,
        "mismatch": 1.665,
        "z_score": 0.467,
        "sigma_30d": 0.0131,
        "eps_drift": 0.0,
        "bin_impact": "low",
        "bin_mismatch": "weak",
        "bin_eps_drift": "noise"
      },
      "strategy": "LONG_CALL",
      "option": {
        "expiry": "2026-08-21",
        "strike": 280.0,
        "bid": 9.5,
        "ask": 9.75,
        "last": 9.5,
        "open_interest": 5543,
        "implied_vol": 0.2744518356323242,
        "spread_ratio": 0.0256,
        "dte": 131
      },
      "outcome": null,
      "last_price": 271.485,
      "current_return": 0.0
    },
    {
      "ticker": "UNH",
      "entry_date": "2026-04-11",
      "features": {
        "impact": 4,
        "surprise": 2,
        "mismatch": 2.854,
        "z_score": 0.229,
        "sigma_30d": 0.0235,
        "eps_drift": 0.0,
        "bin_impact": "low",
        "bin_mismatch": "weak",
        "bin_eps_drift": "noise"
      },
      "strategy": "LONG_PUT",
      "option": {
        "expiry": "2026-08-21",
        "strike": 310.0,
        "bid": 26.5,
        "ask": 26.85,
        "last": 25.8,
        "open_interest": 1218,
        "implied_vol": 0.3238287832641601,
        "spread_ratio": 0.013,
        "dte": 131
      },
      "outcome": null,
      "last_price": 353.5,
      "current_return": 0.0
    },
    {
      "ticker": "LLY",
      "entry_date": "2026-04-11",
      "features": {
        "impact": 8,
        "surprise": 5,
        "mismatch": 4.595,
        "z_score": 0.681,
        "sigma_30d": 0.0213,
        "eps_drift": 0.0,
        "bin_impact": "high",
        "bin_mismatch": "good",
        "bin_eps_drift": "noise"
      },
      "strategy": "LONG_CALL",
      "option": {
        "expiry": "2026-08-21",
        "strike": 980.0,
        "bid": 74.0,
        "ask": 77.3,
        "last": 85.4,
        "open_interest": 255,
        "implied_vol": 0.41737948348999016,
        "spread_ratio": 0.0427,
        "dte": 131
      },
      "outcome": null,
      "last_price": 881.5725,
      "current_return": 0.0
    },
    {
      "ticker": "UNH",
      "entry_date": "2026-04-11",
      "features": {
        "impact": 5,
        "surprise": 3,
        "mismatch": 3.854,
        "z_score": 0.229,
        "sigma_30d": 0.0235,
        "eps_drift": 0.0,
        "bin_impact": "mid",
        "bin_mismatch": "good",
        "bin_eps_drift": "noise"
      },
      "strategy": "LONG_CALL",
      "option": {
        "expiry": "2026-08-21",
        "strike": 330.0,
        "bid": 14.85,
        "ask": 15.55,
        "last": 15.05,
        "open_interest": 2715,
        "implied_vol": 0.3467472552490234,
        "spread_ratio": 0.045,
        "dte": 131
      },
      "outcome": null,
      "last_price": 353.5,
      "current_return": 0.0
    },
    {
      "ticker": "META",
      "entry_date": "2026-04-11",
      "features": {
        "impact": 6,
        "surprise": 7,
        "mismatch": 0.733,
        "z_score": 1.053,
        "sigma_30d": 0.027,
        "eps_drift": 0.0,
        "bin_impact": "mid",
        "bin_mismatch": "weak",
        "bin_eps_drift": "noise"
      },
      "strategy": "LONG_CALL",
      "option": {
        "expiry": "2026-08-21",
        "strike": 700.0,
        "bid": 33.0,
        "ask": 33.4,
        "last": 33.35,
        "open_interest": 2204,
        "implied_vol": 0.390203851928711,
        "spread_ratio": 0.012,
        "dte": 131
      },
      "outcome": null,
      "last_price": 669.105,
      "current_return": 0.0
    },
    {
      "ticker": "MRK",
      "entry_date": "2026-04-11",
      "features": {
        "impact": 7,
        "surprise": 5,
        "mismatch": 2.158,
        "z_score": 0.968,
        "sigma_30d": 0.0148,
        "eps_drift": 0.0,
        "bin_impact": "mid",
        "bin_mismatch": "weak",
        "bin_eps_drift": "noise"
      },
      "strategy": "LONG_CALL",
      "option": {
        "expiry": "2026-09-18",
        "strike": 130.0,
        "bid": 6.0,
        "ask": 6.2,
        "last": 6.05,
        "open_interest": 2663,
        "implied_vol": 0.2979196185302734,
        "spread_ratio": 0.0323,
        "dte": 159
      },
      "outcome": null,
      "last_price": 112.42,
      "current_return": 0.0
    },
    {
      "ticker": "AAPL",
      "entry_date": "2026-04-11",
      "features": {
        "impact": 4,
        "surprise": 2,
        "mismatch": 1.665,
        "z_score": 0.467,
        "sigma_30d": 0.0131,
        "eps_drift": 0.0,
        "bin_impact": "low",
        "bin_mismatch": "weak",
        "bin_eps_drift": "noise"
      },
      "strategy": "LONG_CALL",
      "option": {
        "expiry": "2026-08-21",
        "strike": 280.0,
        "bid": 9.5,
        "ask": 9.75,
        "last": 9.5,
        "open_interest": 5543,
        "implied_vol": 0.2744518356323242,
        "spread_ratio": 0.0256,
        "dte": 131
      },
      "outcome": null,
      "last_price": 271.485,
      "current_return": 0.0
    },
    {
      "ticker": "TSLA",
      "entry_date": "2026-04-11",
      "features": {
        "impact": 4,
        "surprise": 3,
        "mismatch": 0.459,
        "z_score": 0.708,
        "sigma_30d": 0.0235,
        "eps_drift": 0.0,
        "bin_impact": "low",
        "bin_mismatch": "weak",
        "bin_eps_drift": "noise"
      },
      "strategy": "LONG_PUT",
      "option": {
        "expiry": "2026-08-21",
        "strike": 350.0,
        "bid": 36.45,
        "ask": 36.7,
        "last": 37.62,
        "open_interest": 3942,
        "implied_vol": 0.4310969976806641,
        "spread_ratio": 0.0068,
        "dte": 131
      },
      "outcome": null,
      "last_price": 375.6001,
      "current_return": 0.0
    },
    {
      "ticker": "LLY",
      "entry_date": "2026-04-11",
      "features": {
        "impact": 4,
        "surprise": 2,
        "mismatch": 0.595,
        "z_score": 0.681,
        "sigma_30d": 0.0213,
        "eps_drift": 0.0,
        "bin_impact": "low",
        "bin_mismatch": "weak",
        "bin_eps_drift": "noise"
      },
      "strategy": "LONG_CALL",
      "option": {
        "expiry": "2026-08-21",
        "strike": 980.0,
        "bid": 74.0,
        "ask": 77.3,
        "last": 85.4,
        "open_interest": 255,
        "implied_vol": 0.41737948348999016,
        "spread_ratio": 0.0427,
        "dte": 131
      },
      "outcome": null,
      "last_price": 881.47,
      "current_return": 0.0
    },
    {
      "ticker": "LLY",
      "entry_date": "2026-04-11",
      "features": {
        "impact": 4,
        "surprise": 3,
        "mismatch": 0.595,
        "z_score": 0.681,
        "sigma_30d": 0.0213,
        "eps_drift": 0.0,
        "bin_impact": "low",
        "bin_mismatch": "weak",
        "bin_eps_drift": "noise"
      },
      "strategy": "LONG_CALL",
      "option": {
        "expiry": "2026-08-21",
        "strike": 980.0,
        "bid": 74.0,
        "ask": 77.3,
        "last": 85.4,
        "open_interest": 255,
        "implied_vol": 0.41737948348999016,
        "spread_ratio": 0.0427,
        "dte": 131
      },
      "outcome": null,
      "last_price": 881.47,
      "current_return": 0.0
    },
    {
      "ticker": "LLY",
      "entry_date": "2026-04-11",
      "features": {
        "impact": 4,
        "surprise": 3,
        "mismatch": 0.595,
        "z_score": 0.681,
        "sigma_30d": 0.0213,
        "eps_drift": 0.0,
        "bin_impact": "low",
        "bin_mismatch": "weak",
        "bin_eps_drift": "noise"
      },
      "strategy": "LONG_CALL",
      "option": {
        "expiry": "2026-08-21",
        "strike": 980.0,
        "bid": 74.0,
        "ask": 77.3,
        "last": 85.4,
        "open_interest": 255,
        "implied_vol": 0.41737948348999016,
        "spread_ratio": 0.0427,
        "dte": 131
      },
      "outcome": null,
      "last_price": 881.47,
      "current_return": 0.0
    },
    {
      "ticker": "GOOGL",
      "entry_date": "2026-04-13",
      "features": {
        "impact": 5,
        "surprise": 4,
        "mismatch": 4.284,
        "z_score": 0.143,
        "sigma_30d": 0.019,
        "eps_drift": 0.0,
        "bin_impact": "mid",
        "bin_mismatch": "good",
        "bin_eps_drift": "noise"
      },
      "strategy": "LONG_PUT",
      "option": {
        "expiry": "2026-08-21",
        "strike": 320.0,
        "bid": 25.15,
        "ask": 25.8,
        "last": 25.02,
        "open_interest": 1363,
        "implied_vol": 0.3354558642578125,
        "spread_ratio": 0.0252,
        "dte": 129
      },
      "outcome": null,
      "last_price": 339.2775,
      "current_return": 0.0
    },
    {
      "ticker": "AMZN",
      "entry_date": "2026-04-13",
      "features": {
        "impact": 7,
        "surprise": 5,
        "mismatch": 2.124,
        "z_score": 0.975,
        "sigma_30d": 0.0202,
        "eps_drift": 0.0,
        "bin_impact": "mid",
        "bin_mismatch": "weak",
        "bin_eps_drift": "noise"
      },
      "strategy": "LONG_CALL",
      "option": {
        "expiry": "2026-08-21",
        "strike": 260.0,
        "bid": 12.85,
        "ask": 12.95,
        "last": 12.9,
        "open_interest": 46913,
        "implied_vol": 0.373480386352539,
        "spread_ratio": 0.0077,
        "dte": 129
      },
      "outcome": null,
      "last_price": 259.777,
      "current_return": 0.0
    },
    {
      "ticker": "AAPL",
      "entry_date": "2026-04-13",
      "features": {
        "impact": 5,
        "surprise": 3,
        "mismatch": 1.325,
        "z_score": 0.735,
        "sigma_30d": 0.0131,
        "eps_drift": 0.0,
        "bin_impact": "mid",
        "bin_mismatch": "weak",
        "bin_eps_drift": "noise"
      },
      "strategy": "LONG_CALL",
      "option": {
        "expiry": "2026-08-21",
        "strike": 280.0,
        "bid": 8.4,
        "ask": 8.55,
        "last": 8.5,
        "open_interest": 5538,
        "implied_vol": 0.2707287283325196,
        "spread_ratio": 0.0175,
        "dte": 129
      },
      "outcome": null,
      "last_price": 271.485,
      "current_return": 0.0
    },
    {
      "ticker": "MRK",
      "entry_date": "2026-04-14",
      "features": {
        "impact": 8,
        "surprise": 6,
        "mismatch": 3.544,
        "z_score": 0.891,
        "sigma_30d": 0.0147,
        "eps_drift": 0.0,
        "bin_impact": "high",
        "bin_mismatch": "good",
        "bin_eps_drift": "noise"
      },
      "strategy": "LONG_CALL",
      "option": {
        "expiry": "2026-09-18",
        "strike": 130.0,
        "bid": 5.15,
        "ask": 5.5,
        "last": 5.3,
        "open_interest": 2769,
        "implied_vol": 0.2979196185302734,
        "spread_ratio": 0.0636,
        "dte": 156
      },
      "outcome": null,
      "last_price": 112.42,
      "current_return": 0.0
    },
    {
      "ticker": "AVGO",
      "entry_date": "2026-04-14",
      "features": {
        "impact": 8,
        "surprise": 4,
        "mismatch": 3.543,
        "z_score": 0.891,
        "sigma_30d": 0.0274,
        "eps_drift": 0.0,
        "bin_impact": "high",
        "bin_mismatch": "good",
        "bin_eps_drift": "noise"
      },
      "strategy": "LONG_CALL",
      "option": {
        "expiry": "2026-08-21",
        "strike": 400.0,
        "bid": 34.45,
        "ask": 35.2,
        "last": 34.81,
        "open_interest": 2495,
        "implied_vol": 0.47711704528808596,
        "spread_ratio": 0.0213,
        "dte": 128
      },
      "outcome": null,
      "last_price": 414.59,
      "current_return": 0.0
    },
    {
      "ticker": "LLY",
      "entry_date": "2026-04-14",
      "features": {
        "impact": 6,
        "surprise": 5,
        "mismatch": 5.06,
        "z_score": 0.188,
        "sigma_30d": 0.0194,
        "eps_drift": 0.0,
        "bin_impact": "mid",
        "bin_mismatch": "good",
        "bin_eps_drift": "noise"
      },
      "strategy": "LONG_CALL",
      "option": {
        "expiry": "2026-08-21",
        "strike": 980.0,
        "bid": 68.55,
        "ask": 74.5,
        "last": 72.0,
        "open_interest": 255,
        "implied_vol": 0.41673862075805657,
        "spread_ratio": 0.0799,
        "dte": 128
      },
      "outcome": null,
      "last_price": 881.47,
      "current_return": 0.0
    },
    {
      "ticker": "ABBV",
      "entry_date": "2026-04-14",
      "features": {
        "impact": 5,
        "surprise": 4,
        "mismatch": 4.052,
        "z_score": 0.19,
        "sigma_30d": 0.0162,
        "eps_drift": 0.0,
        "bin_impact": "mid",
        "bin_mismatch": "good",
        "bin_eps_drift": "noise"
      },
      "strategy": "LONG_CALL",
      "option": {
        "expiry": "2026-08-21",
        "strike": 230.0,
        "bid": 6.35,
        "ask": 6.75,
        "last": 6.4,
        "open_interest": 516,
        "implied_vol": 0.2898935757446288,
        "spread_ratio": 0.0593,
        "dte": 128
      },
      "outcome": null,
      "last_price": 199.585,
      "current_return": 0.0
    },
    {
      "ticker": "AAPL",
      "entry_date": "2026-04-14",
      "features": {
        "impact": 4,
        "surprise": 3,
        "mismatch": 1.199,
        "z_score": 0.56,
        "sigma_30d": 0.0124,
        "eps_drift": 0.0,
        "bin_impact": "low",
        "bin_mismatch": "weak",
        "bin_eps_drift": "noise"
      },
      "strategy": "LONG_PUT",
      "option": {
        "expiry": "2026-08-21",
        "strike": 260.0,
        "bid": 16.5,
        "ask": 16.7,
        "last": 15.99,
        "open_interest": 3775,
        "implied_vol": 0.2598340618896484,
        "spread_ratio": 0.012,
        "dte": 128
      },
      "outcome": null,
      "last_price": 271.515,
      "current_return": 0.0
    },
    {
      "ticker": "JNJ",
      "entry_date": "2026-04-15",
      "features": {
        "impact": 6,
        "surprise": 5,
        "mismatch": 5.167,
        "z_score": 0.167,
        "sigma_30d": 0.0095,
        "eps_drift": 0.0,
        "bin_impact": "mid",
        "bin_mismatch": "good",
        "bin_eps_drift": "noise"
      },
      "strategy": "LONG_CALL",
      "option": {
        "expiry": "2026-09-18",
        "strike": 250.0,
        "bid": 9.4,
        "ask": 9.9,
        "last": 9.8,
        "open_interest": 4005,
        "implied_vol": 0.2406081799316406,
        "spread_ratio": 0.0505,
        "dte": 155
      },
      "outcome": null,
      "last_price": 228.255,
      "current_return": 0.0
    },
    {
      "ticker": "UNH",
      "entry_date": "2026-04-15",
      "features": {
        "impact": 5,
        "surprise": 3,
        "mismatch": 4.478,
        "z_score": 0.104,
        "sigma_30d": 0.022,
        "eps_drift": 0.0,
        "bin_impact": "mid",
        "bin_mismatch": "good",
        "bin_eps_drift": "noise"
      },
      "strategy": "LONG_CALL",
      "option": {
        "expiry": "2026-08-21",
        "strike": 330.0,
        "bid": 18.7,
        "ask": 19.05,
        "last": 19.45,
        "open_interest": 2810,
        "implied_vol": 0.3555362298583984,
        "spread_ratio": 0.0184,
        "dte": 127
      },
      "outcome": null,
      "last_price": 353.5,
      "current_return": 0.0
    },
    {
      "ticker": "AVGO",
      "entry_date": "2026-04-15",
      "features": {
        "impact": 8,
        "surprise": 4,
        "mismatch": 1.25,
        "z_score": 1.35,
        "sigma_30d": 0.0277,
        "eps_drift": 0.0,
        "bin_impact": "high",
        "bin_mismatch": "weak",
        "bin_eps_drift": "noise"
      },
      "strategy": "LONG_CALL",
      "option": {
        "expiry": "2026-08-21",
        "strike": 400.0,
        "bid": 42.0,
        "ask": 42.6,
        "last": 42.27,
        "open_interest": 2464,
        "implied_vol": 0.48543300216674806,
        "spread_ratio": 0.0141,
        "dte": 127
      },
      "outcome": null,
      "last_price": 414.565,
      "current_return": 0.0
    },
    {
      "ticker": "ABBV",
      "entry_date": "2026-04-15",
      "features": {
        "impact": 4,
        "surprise": 3,
        "mismatch": 3.22,
        "z_score": 0.156,
        "sigma_30d": 0.0168,
        "eps_drift": 0.0,
        "bin_impact": "low",
        "bin_mismatch": "good",
        "bin_eps_drift": "noise"
      },
      "strategy": "LONG_CALL",
      "option": {
        "expiry": "2026-08-21",
        "strike": 230.0,
        "bid": 6.25,
        "ask": 6.65,
        "last": 6.57,
        "open_interest": 513,
        "implied_vol": 0.3078682495117187,
        "spread_ratio": 0.0602,
        "dte": 127
      },
      "outcome": null,
      "last_price": 199.585,
      "current_return": 0.0
    },
    {
      "ticker": "NVDA",
      "entry_date": "2026-04-16",
      "features": {
        "impact": 6,
        "surprise": 3,
        "mismatch": 3.803,
        "z_score": 0.439,
        "sigma_30d": 0.0217,
        "eps_drift": 0.0,
        "bin_impact": "mid",
        "bin_mismatch": "good",
        "bin_eps_drift": "noise"
      },
      "strategy": "LONG_CALL",
      "option": {
        "expiry": "2026-08-21",
        "strike": 200.0,
        "bid": 18.9,
        "ask": 19.0,
        "last": 19.15,
        "open_interest": 14083,
        "implied_vol": 0.42102629760742194,
        "spread_ratio": 0.0053,
        "dte": 126
      },
      "outcome": null,
      "last_price": 202.55,
      "current_return": 0.0
    },
    {
      "ticker": "UNH",
      "entry_date": "2026-04-16",
      "features": {
        "impact": 5,
        "surprise": 3,
        "mismatch": 4.184,
        "z_score": 0.163,
        "sigma_30d": 0.0219,
        "eps_drift": 0.0,
        "bin_impact": "mid",
        "bin_mismatch": "good",
        "bin_eps_drift": "noise"
      },
      "strategy": "LONG_CALL",
      "option": {
        "expiry": "2026-08-21",
        "strike": 330.0,
        "bid": 19.65,
        "ask": 19.9,
        "last": 19.85,
        "open_interest": 2807,
        "implied_vol": 0.3497379479980468,
        "spread_ratio": 0.0126,
        "dte": 126
      },
      "outcome": null,
      "last_price": 353.5,
      "current_return": 0.0
    },
    {
      "ticker": "GOOGL",
      "entry_date": "2026-04-16",
      "features": {
        "impact": 5,
        "surprise": 3,
        "mismatch": 1.566,
        "z_score": 0.687,
        "sigma_30d": 0.0197,
        "eps_drift": 0.0,
        "bin_impact": "mid",
        "bin_mismatch": "weak",
        "bin_eps_drift": "noise"
      },
      "strategy": "LONG_CALL",
      "option": {
        "expiry": "2026-08-21",
        "strike": 350.0,
        "bid": 24.3,
        "ask": 24.45,
        "last": 24.55,
        "open_interest": 7338,
        "implied_vol": 0.3742738354492187,
        "spread_ratio": 0.0061,
        "dte": 126
      },
      "outcome": null,
      "last_price": 339.23,
      "current_return": 0.0
    },
    {
      "ticker": "AMZN",
      "entry_date": "2026-04-16",
      "features": {
        "impact": 7,
        "surprise": 5,
        "mismatch": 6.475,
        "z_score": 0.105,
        "sigma_30d": 0.0207,
        "eps_drift": 0.0,
        "bin_impact": "mid",
        "bin_mismatch": "strong",
        "bin_eps_drift": "noise"
      },
      "strategy": "LONG_CALL",
      "option": {
        "expiry": "2026-08-21",
        "strike": 260.0,
        "bid": 17.6,
        "ask": 17.75,
        "last": 17.9,
        "open_interest": 50681,
        "implied_vol": 0.3848938464355468,
        "spread_ratio": 0.0085,
        "dte": 126
      },
      "outcome": null,
      "last_price": 259.74,
      "current_return": 0.0
    },
    {
      "ticker": "MRK",
      "entry_date": "2026-04-17",
      "features": {
        "impact": 7,
        "surprise": 6,
        "mismatch": 5.409,
        "z_score": 0.318,
        "sigma_30d": 0.0133,
        "eps_drift": 0.0,
        "bin_impact": "mid",
        "bin_mismatch": "good",
        "bin_eps_drift": "noise"
      },
      "strategy": "LONG_CALL",
      "option": {
        "expiry": "2026-09-18",
        "strike": 130.0,
        "bid": 4.15,
        "ask": 4.4,
        "last": 4.15,
        "open_interest": 2854,
        "implied_vol": 0.2933420275878905,
        "spread_ratio": 0.0568,
        "dte": 153
      },
      "outcome": null,
      "last_price": 112.42,
      "current_return": 0.0
    },
    {
      "ticker": "AVGO",
      "entry_date": "2026-04-17",
      "features": {
        "impact": 7,
        "surprise": 3,
        "mismatch": 3.744,
        "z_score": 0.651,
        "sigma_30d": 0.0271,
        "eps_drift": 0.0,
        "bin_impact": "mid",
        "bin_mismatch": "good",
        "bin_eps_drift": "noise"
      },
      "strategy": "LONG_CALL",
      "option": {
        "expiry": "2026-08-21",
        "strike": 440.0,
        "bid": 30.2,
        "ask": 30.85,
        "last": 30.41,
        "open_interest": 1530,
        "implied_vol": 0.47296669616699216,
        "spread_ratio": 0.0211,
        "dte": 125
      },
      "outcome": null,
      "last_price": 414.565,
      "current_return": 0.0
    },
    {
      "ticker": "GOOGL",
      "entry_date": "2026-04-17",
      "features": {
        "impact": 5,
        "surprise": 3,
        "mismatch": 4.27,
        "z_score": 0.146,
        "sigma_30d": 0.0196,
        "eps_drift": 0.0,
        "bin_impact": "mid",
        "bin_mismatch": "good",
        "bin_eps_drift": "noise"
      },
      "strategy": "LONG_CALL",
      "option": {
        "expiry": "2026-08-21",
        "strike": 350.0,
        "bid": 23.5,
        "ask": 23.7,
        "last": 23.32,
        "open_interest": 7319,
        "implied_vol": 0.3613497703552246,
        "spread_ratio": 0.0084,
        "dte": 125
      },
      "outcome": null,
      "last_price": 339.23,
      "current_return": 0.0
    },
    {
      "ticker": "AMZN",
      "entry_date": "2026-04-17",
      "features": {
        "impact": 7,
        "surprise": 5,
        "mismatch": 1.814,
        "z_score": 1.037,
        "sigma_30d": 0.0207,
        "eps_drift": 0.0,
        "bin_impact": "mid",
        "bin_mismatch": "weak",
        "bin_eps_drift": "noise"
      },
      "strategy": "LONG_CALL",
      "option": {
        "expiry": "2026-08-21",
        "strike": 260.0,
        "bid": 19.95,
        "ask": 20.15,
        "last": 20.07,
        "open_interest": 50537,
        "implied_vol": 0.38266608551025383,
        "spread_ratio": 0.0099,
        "dte": 125
      },
      "outcome": null,
      "last_price": 259.74,
      "current_return": 0.0
    },
    {
      "ticker": "LLY",
      "entry_date": "2026-04-17",
      "features": {
        "impact": 7,
        "surprise": 5,
        "mismatch": 1.214,
        "z_score": 1.157,
        "sigma_30d": 0.0192,
        "eps_drift": 0.0,
        "bin_impact": "mid",
        "bin_mismatch": "weak",
        "bin_eps_drift": "noise"
      },
      "strategy": "LONG_CALL",
      "option": {
        "expiry": "2026-08-21",
        "strike": 980.0,
        "bid": 64.45,
        "ask": 68.3,
        "last": 69.2,
        "open_interest": 270,
        "implied_vol": 0.416723362121582,
        "spread_ratio": 0.0564,
        "dte": 125
      },
      "outcome": null,
      "last_price": 881.585,
      "current_return": 0.0
    },
    {
      "ticker": "NVDA",
      "entry_date": "2026-04-17",
      "features": {
        "impact": 5,
        "surprise": 3,
        "mismatch": 2.386,
        "z_score": 0.523,
        "sigma_30d": 0.0204,
        "eps_drift": 0.0,
        "bin_impact": "mid",
        "bin_mismatch": "weak",
        "bin_eps_drift": "noise"
      },
      "strategy": "LONG_CALL",
      "option": {
        "expiry": "2026-08-21",
        "strike": 210.0,
        "bid": 15.3,
        "ask": 15.4,
        "last": 15.2,
        "open_interest": 11743,
        "implied_vol": 0.40515731567382807,
        "spread_ratio": 0.0065,
        "dte": 125
      },
      "outcome": null,
      "last_price": 202.55,
      "current_return": 0.0
    },
    {
      "ticker": "META",
      "entry_date": "2026-04-17",
      "features": {
        "impact": 4,
        "surprise": 5,
        "mismatch": 0.81,
        "z_score": 0.638,
        "sigma_30d": 0.0274,
        "eps_drift": 0.0,
        "bin_impact": "low",
        "bin_mismatch": "weak",
        "bin_eps_drift": "noise"
      },
      "strategy": "LONG_PUT",
      "option": {
        "expiry": "2026-08-21",
        "strike": 710.0,
        "bid": 70.15,
        "ask": 70.7,
        "last": 76.79,
        "open_interest": 1027,
        "implied_vol": 0.34496199478149414,
        "spread_ratio": 0.0078,
        "dte": 125
      },
      "outcome": null,
      "last_price": 669.0,
      "current_return": 0.0
    },
    {
      "ticker": "NVDA",
      "entry_date": "2026-04-20",
      "features": {
        "impact": 7,
        "surprise": 4,
        "mismatch": 5.595,
        "z_score": 0.281,
        "sigma_30d": 0.0201,
        "eps_drift": 0.0,
        "bin_impact": "mid",
        "bin_mismatch": "good",
        "bin_eps_drift": "noise"
      },
      "strategy": "LONG_CALL",
      "option": {
        "expiry": "2026-08-21",
        "strike": 200.0,
        "bid": 18.5,
        "ask": 18.8,
        "last": 18.65,
        "open_interest": 13988,
        "implied_vol": 0.41190163299560545,
        "spread_ratio": 0.016,
        "dte": 122
      },
      "outcome": null,
      "last_price": 202.55,
      "current_return": 0.0
    },
    {
      "ticker": "AMZN",
      "entry_date": "2026-04-20",
      "features": {
        "impact": 7,
        "surprise": 5,
        "mismatch": 4.465,
        "z_score": 0.507,
        "sigma_30d": 0.0208,
        "eps_drift": 0.0,
        "bin_impact": "mid",
        "bin_mismatch": "good",
        "bin_eps_drift": "noise"
      },
      "strategy": "LONG_CALL",
      "option": {
        "expiry": "2026-08-21",
        "strike": 260.0,
        "bid": 16.1,
        "ask": 16.3,
        "last": 16.07,
        "open_interest": 28376,
        "implied_vol": 0.3765626309204102,
        "spread_ratio": 0.0123,
        "dte": 122
      },
      "outcome": null,
      "last_price": 259.74,
      "current_return": 0.0
    },
    {
      "ticker": "META",
      "entry_date": "2026-04-20",
      "features": {
        "impact": 6,
        "surprise": 4,
        "mismatch": 4.958,
        "z_score": 0.208,
        "sigma_30d": 0.0278,
        "eps_drift": 0.0,
        "bin_impact": "mid",
        "bin_mismatch": "good",
        "bin_eps_drift": "noise"
      },
      "strategy": "LONG_CALL",
      "option": {
        "expiry": "2026-08-21",
        "strike": 700.0,
        "bid": 51.1,
        "ask": 51.8,
        "last": 51.01,
        "open_interest": 2652,
        "implied_vol": 0.40440964248657224,
        "spread_ratio": 0.0135,
        "dte": 122
      },
      "outcome": null,
      "last_price": 669.0,
      "current_return": 0.0
    },
    {
      "ticker": "GOOGL",
      "entry_date": "2026-04-20",
      "features": {
        "impact": 5,
        "surprise": 3,
        "mismatch": 2.594,
        "z_score": 0.481,
        "sigma_30d": 0.0195,
        "eps_drift": 0.0,
        "bin_impact": "mid",
        "bin_mismatch": "weak",
        "bin_eps_drift": "noise"
      },
      "strategy": "LONG_CALL",
      "option": {
        "expiry": "2026-08-21",
        "strike": 350.0,
        "bid": 23.7,
        "ask": 24.25,
        "last": 23.78,
        "open_interest": 7611,
        "implied_vol": 0.3670717590332031,
        "spread_ratio": 0.0227,
        "dte": 122
      },
      "outcome": null,
      "last_price": 339.23,
      "current_return": 0.0
    },
    {
      "ticker": "JNJ",
      "entry_date": "2026-04-20",
      "features": {
        "impact": 6,
        "surprise": 5,
        "mismatch": 1.393,
        "z_score": 0.921,
        "sigma_30d": 0.009,
        "eps_drift": 0.0,
        "bin_impact": "mid",
        "bin_mismatch": "weak",
        "bin_eps_drift": "noise"
      },
      "strategy": "LONG_CALL",
      "option": {
        "expiry": "2026-09-18",
        "strike": 250.0,
        "bid": 7.2,
        "ask": 7.65,
        "last": 7.33,
        "open_interest": 4049,
        "implied_vol": 0.23795317718505854,
        "spread_ratio": 0.0588,
        "dte": 150
      },
      "outcome": null,
      "last_price": 228.35,
      "current_return": 0.0
    },
    {
      "ticker": "LLY",
      "entry_date": "2026-04-20",
      "features": {
        "impact": 7,
        "surprise": 6,
        "mismatch": 0.353,
        "z_score": 1.329,
        "sigma_30d": 0.0186,
        "eps_drift": 0.0,
        "bin_impact": "mid",
        "bin_mismatch": "weak",
        "bin_eps_drift": "noise"
      },
      "strategy": "LONG_CALL",
      "option": {
        "expiry": "2026-08-21",
        "strike": 980.0,
        "bid": 65.55,
        "ask": 68.3,
        "last": 63.8,
        "open_interest": 277,
        "implied_vol": 0.41913422668457034,
        "spread_ratio": 0.0403,
        "dte": 122
      },
      "outcome": null,
      "last_price": 881.585,
      "current_return": 0.0
    },
    {
      "ticker": "AVGO",
      "entry_date": "2026-04-20",
      "features": {
        "impact": 7,
        "surprise": 3,
        "mismatch": 6.818,
        "z_score": 0.036,
        "sigma_30d": 0.0276,
        "eps_drift": 0.0,
        "bin_impact": "mid",
        "bin_mismatch": "strong",
        "bin_eps_drift": "noise"
      },
      "strategy": "LONG_CALL",
      "option": {
        "expiry": "2026-08-21",
        "strike": 400.0,
        "bid": 43.0,
        "ask": 44.35,
        "last": 43.85,
        "open_interest": 2628,
        "implied_vol": 0.49065145584106445,
        "spread_ratio": 0.0304,
        "dte": 122
      },
      "outcome": null,
      "last_price": 414.565,
      "current_return": 0.0
    },
    {
      "ticker": "AMZN",
      "entry_date": "2026-04-21",
      "features": {
        "impact": 7,
        "surprise": 4,
        "mismatch": 4.631,
        "z_score": 0.474,
        "sigma_30d": 0.0208,
        "eps_drift": 0.0,
        "bin_impact": "mid",
        "bin_mismatch": "good",
        "bin_eps_drift": "noise"
      },
      "strategy": "LONG_CALL",
      "option": {
        "expiry": "2026-08-21",
        "strike": 280.0,
        "bid": 11.8,
        "ask": 12.0,
        "last": 11.87,
        "open_interest": 40186,
        "implied_vol": 0.37152728088378906,
        "spread_ratio": 0.0167,
        "dte": 121
      },
      "outcome": null,
      "last_price": 259.74,
      "current_return": 0.0
    },
    {
      "ticker": "NVDA",
      "entry_date": "2026-04-21",
      "features": {
        "impact": 6,
        "surprise": 4,
        "mismatch": 5.397,
        "z_score": 0.121,
        "sigma_30d": 0.0197,
        "eps_drift": 0.0,
        "bin_impact": "mid",
        "bin_mismatch": "good",
        "bin_eps_drift": "noise"
      },
      "strategy": "LONG_CALL",
      "option": {
        "expiry": "2026-08-21",
        "strike": 210.0,
        "bid": 15.2,
        "ask": 15.45,
        "last": 15.35,
        "open_interest": 12484,
        "implied_vol": 0.40048817291259764,
        "spread_ratio": 0.0162,
        "dte": 121
      },
      "outcome": null,
      "last_price": 202.55,
      "current_return": 0.0
    },
    {
      "ticker": "META",
      "entry_date": "2026-04-21",
      "features": {
        "impact": 7,
        "surprise": 3,
        "mismatch": 3.517,
        "z_score": 0.697,
        "sigma_30d": 0.0279,
        "eps_drift": 0.0,
        "bin_impact": "mid",
        "bin_mismatch": "good",
        "bin_eps_drift": "noise"
      },
      "strategy": "LONG_CALL",
      "option": {
        "expiry": "2026-08-21",
        "strike": 700.0,
        "bid": 50.7,
        "ask": 51.7,
        "last": 51.5,
        "open_interest": 2648,
        "implied_vol": 0.3983214465332031,
        "spread_ratio": 0.0193,
        "dte": 121
      },
      "outcome": null,
      "last_price": 669.0,
      "current_return": 0.0
    },
    {
      "ticker": "AVGO",
      "entry_date": "2026-04-21",
      "features": {
        "impact": 7,
        "surprise": 4,
        "mismatch": 3.202,
        "z_score": 0.76,
        "sigma_30d": 0.0272,
        "eps_drift": 0.0,
        "bin_impact": "mid",
        "bin_mismatch": "good",
        "bin_eps_drift": "noise"
      },
      "strategy": "LONG_CALL",
      "option": {
        "expiry": "2026-08-21",
        "strike": 400.0,
        "bid": 42.5,
        "ask": 43.25,
        "last": 42.6,
        "open_interest": 2629,
        "implied_vol": 0.47653721710205077,
        "spread_ratio": 0.0173,
        "dte": 121
      },
      "outcome": null,
      "last_price": 414.565,
      "current_return": 0.0
    },
    {
      "ticker": "AAPL",
      "entry_date": "2026-04-21",
      "features": {
        "impact": 4,
        "surprise": 2,
        "mismatch": 3.791,
        "z_score": 0.042,
        "sigma_30d": 0.0133,
        "eps_drift": 0.0,
        "bin_impact": "low",
        "bin_mismatch": "good",
        "bin_eps_drift": "noise"
      },
      "strategy": "LONG_CALL",
      "option": {
        "expiry": "2026-08-21",
        "strike": 300.0,
        "bid": 6.95,
        "ask": 7.1,
        "last": 7.08,
        "open_interest": 8972,
        "implied_vol": 0.2763133892822265,
        "spread_ratio": 0.0211,
        "dte": 121
      },
      "outcome": null,
      "last_price": 271.46,
      "current_return": 0.0
    },
    {
      "ticker": "GOOGL",
      "entry_date": "2026-04-21",
      "features": {
        "impact": 5,
        "surprise": 3,
        "mismatch": 2.586,
        "z_score": 0.483,
        "sigma_30d": 0.0195,
        "eps_drift": 0.0,
        "bin_impact": "mid",
        "bin_mismatch": "weak",
        "bin_eps_drift": "noise"
      },
      "strategy": "LONG_CALL",
      "option": {
        "expiry": "2026-08-21",
        "strike": 350.0,
        "bid": 23.0,
        "ask": 24.2,
        "last": 23.25,
        "open_interest": 7655,
        "implied_vol": 0.37030658996582033,
        "spread_ratio": 0.0496,
        "dte": 121
      },
      "outcome": null,
      "last_price": 339.23,
      "current_return": 0.0
    },
    {
      "ticker": "PFE",
      "entry_date": "2026-04-21",
      "features": {
        "impact": 5,
        "surprise": 4,
        "mismatch": 1.595,
        "z_score": 0.681,
        "sigma_30d": 0.0133,
        "eps_drift": 0.0,
        "bin_impact": "mid",
        "bin_mismatch": "weak",
        "bin_eps_drift": "noise"
      },
      "strategy": "LONG_CALL",
      "option": {
        "expiry": "2026-09-18",
        "strike": 30.0,
        "bid": 0.66,
        "ask": 0.7,
        "last": 0.66,
        "open_interest": 26415,
        "implied_vol": 0.23438265625,
        "spread_ratio": 0.0571,
        "dte": 149
      },
      "outcome": null,
      "last_price": 26.8514,
      "current_return": 0.0
    },
    {
      "ticker": "LLY",
      "entry_date": "2026-04-22",
      "features": {
        "impact": 6,
        "surprise": 5,
        "mismatch": 5.305,
        "z_score": 0.139,
        "sigma_30d": 0.0191,
        "eps_drift": 0.0,
        "bin_impact": "mid",
        "bin_mismatch": "good",
        "bin_eps_drift": "noise"
      },
      "strategy": "LONG_CALL",
      "option": {
        "expiry": "2026-08-21",
        "strike": 980.0,
        "bid": 57.0,
        "ask": 62.65,
        "last": 59.0,
        "open_interest": 281,
        "implied_vol": 0.414594782333374,
        "spread_ratio": 0.0902,
        "dte": 120
      },
      "outcome": null,
      "last_price": 881.47,
      "current_return": 0.0
    },
    {
      "ticker": "META",
      "entry_date": "2026-04-22",
      "features": {
        "impact": 6,
        "surprise": 3,
        "mismatch": 5.087,
        "z_score": 0.183,
        "sigma_30d": 0.0277,
        "eps_drift": 0.0,
        "bin_impact": "mid",
        "bin_mismatch": "good",
        "bin_eps_drift": "noise"
      },
      "strategy": "LONG_CALL",
      "option": {
        "expiry": "2026-08-21",
        "strike": 700.0,
        "bid": 50.65,
        "ask": 51.3,
        "last": 51.03,
        "open_interest": 2580,
        "implied_vol": 0.3998167929077149,
        "spread_ratio": 0.0127,
        "dte": 120
      },
      "outcome": null,
      "last_price": 669.0,
      "current_return": 0.0
    },
    {
      "ticker": "NVDA",
      "entry_date": "2026-04-22",
      "features": {
        "impact": 6,
        "surprise": 4,
        "mismatch": 3.729,
        "z_score": 0.454,
        "sigma_30d": 0.0198,
        "eps_drift": 0.0,
        "bin_impact": "mid",
        "bin_mismatch": "good",
        "bin_eps_drift": "noise"
      },
      "strategy": "LONG_CALL",
      "option": {
        "expiry": "2026-08-21",
        "strike": 200.0,
        "bid": 19.15,
        "ask": 19.5,
        "last": 19.45,
        "open_interest": 14273,
        "implied_vol": 0.4239559558105469,
        "spread_ratio": 0.0179,
        "dte": 120
      },
      "outcome": null,
      "last_price": 202.52,
      "current_return": 0.0
    },
    {
      "ticker": "AVGO",
      "entry_date": "2026-04-22",
      "features": {
        "impact": 7,
        "surprise": 4,
        "mismatch": 2.48,
        "z_score": 0.904,
        "sigma_30d": 0.0272,
        "eps_drift": 0.0,
        "bin_impact": "mid",
        "bin_mismatch": "weak",
        "bin_eps_drift": "noise"
      },
      "strategy": "LONG_CALL",
      "option": {
        "expiry": "2026-08-21",
        "strike": 440.0,
        "bid": 31.1,
        "ask": 32.4,
        "last": 29.64,
        "open_interest": 1626,
        "implied_vol": 0.4735770416259766,
        "spread_ratio": 0.0401,
        "dte": 120
      },
      "outcome": null,
      "last_price": 414.52,
      "current_return": 0.0
    },
    {
      "ticker": "AMZN",
      "entry_date": "2026-04-22",
      "features": {
        "impact": 7,
        "surprise": 4,
        "mismatch": 1.706,
        "z_score": 1.059,
        "sigma_30d": 0.0199,
        "eps_drift": 0.0,
        "bin_impact": "mid",
        "bin_mismatch": "weak",
        "bin_eps_drift": "noise"
      },
      "strategy": "LONG_CALL",
      "option": {
        "expiry": "2026-08-21",
        "strike": 260.0,
        "bid": 18.25,
        "ask": 18.5,
        "last": 18.46,
        "open_interest": 28308,
        "implied_vol": 0.3657900335693359,
        "spread_ratio": 0.0135,
        "dte": 120
      },
      "outcome": null,
      "last_price": 259.75,
      "current_return": 0.0
    },
    {
      "ticker": "GOOGL",
      "entry_date": "2026-04-22",
      "features": {
        "impact": 4,
        "surprise": 3,
        "mismatch": 3.881,
        "z_score": 0.024,
        "sigma_30d": 0.0199,
        "eps_drift": 0.0,
        "bin_impact": "low",
        "bin_mismatch": "good",
        "bin_eps_drift": "noise"
      },
      "strategy": "LONG_PUT",
      "option": {
        "expiry": "2026-08-21",
        "strike": 370.0,
        "bid": 43.6,
        "ask": 46.35,
        "last": 45.0,
        "open_interest": 290,
        "implied_vol": 0.3346318978881836,
        "spread_ratio": 0.0593,
        "dte": 120
      },
      "outcome": null,
      "last_price": 339.225,
      "current_return": 0.0
    },
    {
      "ticker": "AAPL",
      "entry_date": "2026-04-22",
      "features": {
        "impact": 4,
        "surprise": 2,
        "mismatch": 1.008,
        "z_score": 0.598,
        "sigma_30d": 0.0141,
        "eps_drift": 0.0,
        "bin_impact": "low",
        "bin_mismatch": "weak",
        "bin_eps_drift": "noise"
      },
      "strategy": "LONG_PUT",
      "option": {
        "expiry": "2026-08-21",
        "strike": 300.0,
        "bid": 34.5,
        "ask": 35.35,
        "last": 32.18,
        "open_interest": 10186,
        "implied_vol": 0.25580578186035163,
        "spread_ratio": 0.024,
        "dte": 120
      },
      "outcome": null,
      "last_price": 271.46,
      "current_return": 0.0
    },
    {
      "ticker": "NVDA",
      "entry_date": "2026-04-23",
      "features": {
        "impact": 7,
        "surprise": 4,
        "mismatch": 3.571,
        "z_score": 0.686,
        "sigma_30d": 0.0198,
        "eps_drift": 0.0,
        "bin_impact": "mid",
        "bin_mismatch": "good",
        "bin_eps_drift": "noise"
      },
      "strategy": "LONG_CALL",
      "option": {
        "expiry": "2026-09-18",
        "strike": 220.0,
        "bid": 15.2,
        "ask": 15.45,
        "last": 15.3,
        "open_interest": 27649,
        "implied_vol": 0.434148724975586,
        "spread_ratio": 0.0162,
        "dte": 147
      },
      "outcome": null,
      "last_price": 202.52,
      "current_return": 0.0
    },
    {
      "ticker": "AMZN",
      "entry_date": "2026-04-23",
      "features": {
        "impact": 7,
        "surprise": 5,
        "mismatch": 1.857,
        "z_score": 1.029,
        "sigma_30d": 0.0201,
        "eps_drift": 0.0,
        "bin_impact": "mid",
        "bin_mismatch": "weak",
        "bin_eps_drift": "noise"
      },
      "strategy": "LONG_CALL",
      "option": {
        "expiry": "2026-09-18",
        "strike": 280.0,
        "bid": 14.8,
        "ask": 15.0,
        "last": 15.07,
        "open_interest": 11760,
        "implied_vol": 0.37616590637207037,
        "spread_ratio": 0.0133,
        "dte": 147
      },
      "outcome": null,
      "last_price": 259.75,
      "current_return": 0.0
    },
    {
      "ticker": "LLY",
      "entry_date": "2026-04-23",
      "features": {
        "impact": 7,
        "surprise": 6,
        "mismatch": 1.424,
        "z_score": 1.115,
        "sigma_30d": 0.0189,
        "eps_drift": 0.0,
        "bin_impact": "mid",
        "bin_mismatch": "weak",
        "bin_eps_drift": "noise"
      },
      "strategy": "LONG_CALL",
      "option": {
        "expiry": "2026-09-18",
        "strike": 1000.0,
        "bid": 62.05,
        "ask": 68.0,
        "last": 61.75,
        "open_interest": 380,
        "implied_vol": 0.4185849157714844,
        "spread_ratio": 0.0875,
        "dte": 147
      },
      "outcome": null,
      "last_price": 881.47,
      "current_return": 0.0
    },
    {
      "ticker": "JNJ",
      "entry_date": "2026-04-23",
      "features": {
        "impact": 6,
        "surprise": 5,
        "mismatch": 0.487,
        "z_score": 1.103,
        "sigma_30d": 0.0092,
        "eps_drift": 0.0,
        "bin_impact": "mid",
        "bin_mismatch": "weak",
        "bin_eps_drift": "noise"
      },
      "strategy": "LONG_CALL",
      "option": {
        "expiry": "2026-09-18",
        "strike": 250.0,
        "bid": 4.95,
        "ask": 5.5,
        "last": 5.0,
        "open_interest": 4242,
        "implied_vol": 0.22385419708251947,
        "spread_ratio": 0.1,
        "dte": 147
      },
      "outcome": null,
      "last_price": 228.35,
      "current_return": 0.0
    },
    {
      "ticker": "META",
      "entry_date": "2026-04-24",
      "features": {
        "impact": 7,
        "surprise": 4,
        "mismatch": 5.476,
        "z_score": 0.305,
        "sigma_30d": 0.0278,
        "eps_drift": 0.0,
        "bin_impact": "mid",
        "bin_mismatch": "good",
        "bin_eps_drift": "noise"
      },
      "strategy": "LONG_CALL",
      "option": {
        "expiry": "2026-09-18",
        "strike": 700.0,
        "bid": 51.2,
        "ask": 52.2,
        "last": 49.5,
        "open_interest": 3469,
        "implied_vol": 0.3833374655151367,
        "spread_ratio": 0.0192,
        "dte": 146
      },
      "outcome": null,
      "last_price": 669.0,
      "current_return": 0.0
    }
  ],
  "closed_trades": [],
  "model_weights": {
    "impact": 0.35,
    "mismatch": 0.45,
    "eps_drift": 0.2
  }
}